stringcontext/__init__.py
stringcontext/stringcontext.py
stringcontext-1.0.0.dist-info/LICENSE
stringcontext-1.0.0.dist-info/METADATA
stringcontext-1.0.0.dist-info/WHEEL
stringcontext-1.0.0.dist-info/top_level.txt
stringcontext-1.0.0.dist-info/zip-safe
stringcontext-1.0.0.dist-info/RECORD
