Metadata-Version: 2.1
Name: stringcontext
Version: 1.0.0
Summary: Get the context around an index location in a string
Home-page: https://github.com/wesinator/stringcontext
Author: wesinator
Author-email: 13hurdw@gmail.com
License: UNKNOWN
Platform: UNKNOWN
Classifier: Intended Audience :: Developers
Classifier: License :: OSI Approved :: MIT License
Classifier: Natural Language :: English
Classifier: Programming Language :: Python :: 3
